netutils/__init__.py
netutils/_private/version.py
netutils/acl.py
netutils/asn.py
netutils/bandwidth.py
netutils/banner.py
netutils/config/__init__.py
netutils/config/clean.py
netutils/config/compliance.py
netutils/config/conversion.py
netutils/config/parser.py
netutils/config/utils.py
netutils/constants.py
netutils/data_files/__init__.py
netutils/data_files/oui_mappings.py
netutils/data_files/protocol_mappings.py
netutils/data_files/protocol_number_mappings.py
netutils/dns.py
netutils/hash.py
netutils/interface.py
netutils/ip.py
netutils/lib_helpers.py
netutils/lib_mapper.py
netutils/mac.py
netutils/nist.py
netutils/os_version.py
netutils/password.py
netutils/ping.py
netutils/protocol_mapper.py
netutils/py.typed
netutils/regex.py
netutils/route.py
netutils/running_config.py
netutils/time.py
netutils/utils.py
netutils/vlan.py
netutils-1.17.0.dist-info/LICENSE
netutils-1.17.0.dist-info/METADATA
netutils-1.17.0.dist-info/WHEEL
netutils-1.17.0.dist-info/RECORD
