Metadata-Version: 2.3
Name: netutils
Version: 1.17.0
Summary: Common helper functions useful in network automation.
License: Apache-2.0
Keywords: netutils,network utils,network utilities,net-utils
Author: Network to Code, LLC
Author-email: opensource@networktocode.com
Requires-Python: >=3.10,<3.14
Classifier: Development Status :: 5 - Production/Stable
Classifier: Intended Audience :: Developers
Classifier: License :: OSI Approved :: Apache Software License
Classifier: Programming Language :: Python :: 3
Classifier: Programming Language :: Python :: 3.10
Classifier: Programming Language :: Python :: 3.11
Classifier: Programming Language :: Python :: 3.12
Classifier: Programming Language :: Python :: 3.13
Provides-Extra: optionals
Requires-Dist: jsonschema (>=4.17.3,<5.0.0) ; extra == "optionals"
Requires-Dist: legacycrypt (==0.3) ; extra == "optionals"
Requires-Dist: napalm (>=4.0.0,<5.0.0) ; extra == "optionals"
Project-URL: Documentation, https://netutils.readthedocs.io
Project-URL: Homepage, https://netutils.readthedocs.io
Project-URL: Repository, https://github.com/networktocode/netutils
